{"config": [{"config": {"defaultAggregated": true, "geoms": ["auto"], "coordSystem": "generic", "limit": -1, "timezoneDisplayOffset": 0}, "encodings": {"dimensions": [{"fid": "time", "name": "time", "basename": "time", "semanticType": "temporal", "analyticType": "dimension", "offset": 0}, {"fid": "Quarter_Year", "name": "Quarter_Year", "basename": "Quarter_Year", "semanticType": "nominal", "analyticType": "dimension", "offset": 0}, {"fid": "Year", "name": "Year", "basename": "Year", "semanticType": "quantitative", "analyticType": "dimension", "offset": 0}, {"fid": "Quarter", "name": "Quarter", "basename": "Quarter", "semanticType": "quantitative", "analyticType": "dimension", "offset": 0}, {"fid": "Data_Type", "name": "Data_Type", "basename": "Data_Type", "semanticType": "nominal", "analyticType": "dimension", "offset": 0}, {"fid": "Seasonality_Detected", "name": "Seasonality_Detected", "basename": "Seasonality_Detected", "semanticType": "nominal", "analyticType": "dimension", "offset": 0}, {"fid": "Forecast_Type", "name": "Forecast_Type", "basename": "Forecast_Type", "semanticType": "nominal", "analyticType": "dimension", "offset": 0}, {"fid": "Trend_Segment", "name": "Trend_Segment", "basename": "Trend_Segment", "semanticType": "nominal", "analyticType": "dimension", "offset": 0}, {"fid": "Trend_Direction", "name": "Trend_Direction", "basename": "Trend_Direction", "semanticType": "nominal", "analyticType": "dimension", "offset": 0}, {"fid": "Segment_Length", "name": "Segment_Length", "basename": "Segment_Length", "semanticType": "quantitative", "analyticType": "dimension", "offset": 0}, {"fid": "Performance_Category", "name": "Performance_Category", "basename": "Performance_Category", "semanticType": "nominal", "analyticType": "dimension", "offset": 0}, {"fid": "gw_paint_fid", "analyticType": "dimension", "name": "Paint Field", "semanticType": "nominal", "computed": true, "expression": {"op": "paint", "as": "gw_paint_fid", "params": [{"type": "newmap", "value": {"dict": {"1": {"name": "L_1", "color": "#4c78a8"}, "2": {"name": "L_2", "color": "#f58518"}, "3": {"name": "L_3", "color": "#e45756"}, "4": {"name": "L_4", "color": "#72b7b2"}, "5": {"name": "L_5", "color": "#54a24b"}, "6": {"name": "L_6", "color": "#eeca3b"}, "7": {"name": "L_7", "color": "#b279a2"}, "8": {"name": "L_8", "color": "#ff9da6"}, "9": {"name": "L_9", "color": "#9d755d"}, "10": {"name": "L_10", "color": "#bab0ac"}}, "facets": [{"map": "Y2DAC5gB", "dimensions": [{"domain": {"type": "nominal", "value": ["2017Q3", "2017Q4", "2018Q1", "2018Q2", "2018Q3", "2018Q4", "2019Q1", "2019Q2", "2019Q3", "2019Q4", "2020Q1", "2020Q2", "2020Q3", "2020Q4", "2021Q1", "2021Q2", "2021Q3", "2021Q4", "2022Q1", "2022Q2", "2022Q3", "2022Q4", "2023Q1", "2023Q2", "2023Q3", "2023Q4", "2024Q1", "2024Q2", "2024Q3", "2024Q4", "2025Q1", "2025Q2"], "width": 32}, "fid": "Quarter_Year"}], "usedColor": [1, 3]}], "usedColor": [1, 3]}}]}}, {"fid": "gw_mea_key_fid", "name": "Measure names", "analyticType": "dimension", "semanticType": "nominal"}], "measures": [{"fid": "close", "name": "close", "basename": "close", "analyticType": "measure", "semanticType": "quantitative", "aggName": "sum", "offset": 0}, {"fid": "Total Revenue", "name": "Total Revenue", "basename": "Total Revenue", "analyticType": "measure", "semanticType": "quantitative", "aggName": "sum", "offset": 0}, {"fid": "Net Income", "name": "Net Income", "basename": "Net Income", "analyticType": "measure", "semanticType": "quantitative", "aggName": "sum", "offset": 0}, {"fid": "Operating Income", "name": "Operating Income", "basename": "Operating Income", "analyticType": "measure", "semanticType": "quantitative", "aggName": "sum", "offset": 0}, {"fid": "Total Assets", "name": "Total Assets", "basename": "Total Assets", "analyticType": "measure", "semanticType": "quantitative", "aggName": "sum", "offset": 0}, {"fid": "Total Equity", "name": "Total Equity", "basename": "Total Equity", "analyticType": "measure", "semanticType": "quantitative", "aggName": "sum", "offset": 0}, {"fid": "Total Debt", "name": "Total Debt", "basename": "Total Debt", "analyticType": "measure", "semanticType": "quantitative", "aggName": "sum", "offset": 0}, {"fid": "Interest Expense", "name": "Interest Expense", "basename": "Interest Expense", "analyticType": "measure", "semanticType": "quantitative", "aggName": "sum", "offset": 0}, {"fid": "Basic EPS", "name": "Basic EPS", "basename": "Basic EPS", "analyticType": "measure", "semanticType": "quantitative", "aggName": "sum", "offset": 0}, {"fid": "Operating margin %", "name": "Operating margin %", "basename": "Operating margin %", "analyticType": "measure", "semanticType": "quantitative", "aggName": "sum", "offset": 0}, {"fid": "Gross margin %", "name": "Gross margin %", "basename": "Gross margin %", "analyticType": "measure", "semanticType": "quantitative", "aggName": "sum", "offset": 0}, {"fid": "Free cash flow", "name": "Free cash flow", "basename": "Free cash flow", "analyticType": "measure", "semanticType": "quantitative", "aggName": "sum", "offset": 0}, {"fid": "Total inventory", "name": "Total inventory", "basename": "Total inventory", "analyticType": "measure", "semanticType": "quantitative", "aggName": "sum", "offset": 0}, {"fid": "Accounts receivable - trade, net", "name": "Accounts receivable - trade, net", "basename": "Accounts receivable - trade, net", "analyticType": "measure", "semanticType": "quantitative", "aggName": "sum", "offset": 0}, {"fid": "Accounts payable", "name": "Accounts payable", "basename": "Accounts payable", "analyticType": "measure", "semanticType": "quantitative", "aggName": "sum", "offset": 0}, {"fid": "GDP Growth Rate", "name": "GDP Growth Rate", "basename": "GDP Growth Rate", "analyticType": "measure", "semanticType": "quantitative", "aggName": "sum", "offset": 0}, {"fid": "Interest Rate", "name": "Interest Rate", "basename": "Interest Rate", "analyticType": "measure", "semanticType": "quantitative", "aggName": "sum", "offset": 0}, {"fid": "Inflation Rate", "name": "Inflation Rate", "basename": "Inflation Rate", "analyticType": "measure", "semanticType": "quantitative", "aggName": "sum", "offset": 0}, {"fid": "year", "name": "year", "basename": "year", "analyticType": "measure", "semanticType": "quantitative", "aggName": "sum", "offset": 0}, {"fid": "quarter", "name": "quarter", "basename": "quarter", "analyticType": "measure", "semanticType": "quantitative", "aggName": "sum", "offset": 0}, {"fid": "Net Margin", "name": "Net Margin", "basename": "Net Margin", "analyticType": "measure", "semanticType": "quantitative", "aggName": "sum", "offset": 0}, {"fid": "Revenue_QoQ_Growth", "name": "Revenue_QoQ_Growth", "basename": "Revenue_QoQ_Growth", "analyticType": "measure", "semanticType": "quantitative", "aggName": "sum", "offset": 0}, {"fid": "Income_QoQ_Growth", "name": "Income_QoQ_Growth", "basename": "Income_QoQ_Growth", "analyticType": "measure", "semanticType": "quantitative", "aggName": "sum", "offset": 0}, {"fid": "Margin_Change", "name": "Margin_Change", "basename": "Margin_Change", "analyticType": "measure", "semanticType": "quantitative", "aggName": "sum", "offset": 0}, {"fid": "Revenue_YoY_Growth", "name": "Revenue_YoY_Growth", "basename": "Revenue_YoY_Growth", "analyticType": "measure", "semanticType": "quantitative", "aggName": "sum", "offset": 0}, {"fid": "Income_YoY_Growth", "name": "Income_YoY_Growth", "basename": "Income_YoY_Growth", "analyticType": "measure", "semanticType": "quantitative", "aggName": "sum", "offset": 0}, {"fid": "Trend_R_Squared", "name": "Trend_R_Squared", "basename": "Trend_R_Squared", "analyticType": "measure", "semanticType": "quantitative", "aggName": "sum", "offset": 0}, {"fid": "Seasonal_Revenue_Pattern", "name": "Seasonal_Revenue_Pattern", "basename": "Seasonal_Revenue_Pattern", "analyticType": "measure", "semanticType": "quantitative", "aggName": "sum", "offset": 0}, {"fid": "Seasonal_Margin_Pattern", "name": "Seasonal_Margin_Pattern", "basename": "Seasonal_Margin_Pattern", "analyticType": "measure", "semanticType": "quantitative", "aggName": "sum", "offset": 0}, {"fid": "Revenue_Billions", "name": "Revenue_Billions", "basename": "Revenue_Billions", "analyticType": "measure", "semanticType": "quantitative", "aggName": "sum", "offset": 0}, {"fid": "Income_Billions", "name": "Income_Billions", "basename": "Income_Billions", "analyticType": "measure", "semanticType": "quantitative", "aggName": "sum", "offset": 0}, {"fid": "gw_count_fid", "name": "Row count", "analyticType": "measure", "semanticType": "quantitative", "aggName": "sum", "computed": true, "expression": {"op": "one", "params": [], "as": "gw_count_fid"}}, {"fid": "gw_mea_val_fid", "name": "Measure values", "analyticType": "measure", "semanticType": "quantitative", "aggName": "sum"}], "rows": [{"fid": "Total Revenue", "name": "Total Revenue", "basename": "Total Revenue", "analyticType": "measure", "semanticType": "quantitative", "aggName": "sum", "offset": 0}, {"fid": "Net Income", "name": "Net Income", "basename": "Net Income", "analyticType": "measure", "semanticType": "quantitative", "aggName": "sum", "offset": 0}], "columns": [{"fid": "Quarter_Year", "name": "Quarter_Year", "basename": "Quarter_Year", "semanticType": "nominal", "analyticType": "dimension", "offset": 0}], "color": [{"fid": "Data_Type", "name": "Data_Type", "basename": "Data_Type", "semanticType": "nominal", "analyticType": "dimension", "offset": 0}], "opacity": [], "size": [], "shape": [], "radius": [], "theta": [], "longitude": [], "latitude": [], "geoId": [], "details": [], "filters": [], "text": []}, "layout": {"showActions": false, "showTableSummary": false, "stack": "stack", "interactiveScale": false, "zeroScale": true, "size": {"mode": "auto", "width": 823, "height": 546}, "format": {}, "geoKey": "name", "resolve": {"x": false, "y": false, "color": false, "opacity": false, "shape": false, "size": false}}, "visId": "gw_O_ah", "name": "Chart 1"}], "chart_map": {}, "version": "0.4.9.15", "workflow_list": [{"workflow": [{"type": "view", "query": [{"op": "aggregate", "groupBy": ["Quarter_Year", "Data_Type"], "measures": [{"field": "Total Revenue", "agg": "sum", "asFieldKey": "Total Revenue_sum"}, {"field": "Net Income", "agg": "sum", "asFieldKey": "Net Income_sum"}]}]}]}]}